chumbot/__init__.py
chumbot/backend/chumshell.py
chumbot/backend/client.py
chumbot/backend/clips.py
chumbot/backend/constants.py
chumbot/cli.py
chumbot/client_interface.py
chumbot-0.7.3.dist-info/LICENSE
chumbot-0.7.3.dist-info/METADATA
chumbot-0.7.3.dist-info/WHEEL
chumbot-0.7.3.dist-info/entry_points.txt
chumbot-0.7.3.dist-info/RECORD
