Metadata-Version: 2.1
Name: chumbot
Version: 0.7.3
Summary: A chummy soundboard bot client for Mumble.
Home-page: https://github.com/Boogie3D/chumbot
License: Apache-2.0
Keywords: mumble,bot,pymumble,sound,soundboard,meme
Author: Steven Anaya
Author-email: anayastevenr@gmail.com
Requires-Python: >=3.7,<4.0
Classifier: Development Status :: 3 - Alpha
Classifier: Environment :: Console
Classifier: Intended Audience :: End Users/Desktop
Classifier: Intended Audience :: Other Audience
Classifier: License :: OSI Approved :: Apache Software License
Classifier: Natural Language :: English
Classifier: Operating System :: OS Independent
Classifier: Programming Language :: Python :: 3
Classifier: Programming Language :: Python :: 3.7
Classifier: Programming Language :: Python :: 3.8
Classifier: Programming Language :: Python :: 3.9
Classifier: Programming Language :: Python :: 3.10
Classifier: Programming Language :: Python :: 3.11
Classifier: Programming Language :: Python :: Implementation :: CPython
Classifier: Topic :: Communications :: Chat
Requires-Dist: pymumble (>=1.6.1,<2.0.0)
Project-URL: Repository, https://github.com/Boogie3D/chumbot
